<?xml version='1.0' encoding='us-ascii'?>

<tunnelxml tunnelversion="version2014-08-01 Austria" tunnelproject="cuccaustria" tunneluser="austria14" tunneldate="2015-08-02 14:20:56">
<sketch splined="0" locoffsetx="1.2677778" locoffsety="-1.0922222" locoffsetz="2.03" realpaperscale="1.0">
	<skpath from="0" to="1" linestyle="connective">
		<pathcodes>
			<pctext style="survey" nodeposxrel="-1.0" nodeposyrel="-1.0">*file_begin&space;&quot;/home/martin/Repositories/loser/caves/264/gosserwager.svx&quot;&space;&quot;&quot;&newline;*begin&space;gosserwager&newline;&newline;*export&space;8&space;9&space;6&newline;&newline;;&space;Cave:&space;Balkonhohle&space;(264)&newline;;&space;Area&space;in&space;cave/QM:&space;&newline;*title&space;&quot;Gosser&space;Wager&quot;&newline;*date&space;2015.07.28&newline;*team&space;Insts&space;Jacob&space;Podesta&newline;*team&space;Notes&space;Martin&space;Green&newline;*team&space;Tape&space;Elliott&space;Smith&newline;*instrument&space;Compass&space;Blue&space;Silva,&space;Clino&space;Yellow&space;#3&newline;;&space;Calibration:&space;204&space;145/+44&space;146/+43&space;144/+43&newline;;&space;Survey&space;folder&space;reference:&space;2015#23&newline;*calibrate&space;tape&space;+0.30&tab;;&space;+ve&space;if&space;tape&space;was&space;too&space;short,&space;-ve&space;if&space;too&space;long&newline;&newline;;&space;Centreline&space;data&newline;*data&space;normal&space;from&space;&space;to&space;&space;&space;tape&space;&space;&space;&space;&space;&space;compass&space;&space;&space;clino&tab;backcompass&tab;backclino&newline;1&tab;2&tab;3.10&tab;355&tab;+20&tab;180&tab;-20&newline;2&tab;3&tab;2.40&tab;035&tab;+30&tab;210&tab;-25&tab;&newline;3&tab;4&tab;4.10&tab;007&tab;+15&tab;-&tab;-&newline;3&tab;5&tab;4.00&tab;330&tab;+45&tab;-&tab;-&newline;1&tab;6&tab;2.94&tab;085&tab;+30&tab;286&tab;-17&newline;6&tab;7&tab;8.90&tab;179&tab;-06&tab;358&tab;+06&newline;7&tab;8&tab;3.04&tab;186&tab;-37&tab;009&tab;+35&newline;9&tab;8&tab;9.95&tab;-&tab;down&tab;-&tab;-&newline;&newline;;-----------&newline;;recorded&space;station&space;details&newline;;(RP=&space;Red&space;Nail&space;Polish,&space;LHW/RHW=Left/Right&space;Hand&space;Wall,&space;PM=Pencil&space;Mark)&newline;;(leave&space;commented-out)&newline;;[Red]&space;nail&space;varnish&space;markings&newline;&newline;&newline;&newline;;LRUDs&space;arranged&space;into&space;passage&space;tubes&newline;*data&space;passage&space;station&space;left&space;right&space;up&space;down&space;&newline;1&tab;0.0&tab;1.2&tab;1.0&tab;1.3&tab;;RP&space;LHW&newline;2&tab;0.1&tab;0.7&tab;1.6&tab;1.0&tab;;RP&tab;LHW&newline;3&tab;0.7&tab;0.3&tab;1.6&tab;1.8&tab;;RP&space;RHW&newline;4&space;&tab;-&tab;-&tab;-&tab;-&tab;;unmarked&space;end&space;of&space;passage&newline;5&space;&tab;-&tab;-&tab;-&tab;-&tab;;unmarked&space;end&space;of&space;passage&newline;6&tab;0.5&tab;0.1&tab;1.4&tab;3.6&tab;;RP&space;RHW&newline;7&tab;0.4&tab;0.3&tab;1.0&tab;1.8&tab;;RP&space;RHW&newline;8&tab;0.9&tab;1.2&tab;-&tab;6.7&tab;;RP&space;pencil&space;#8&space;bottom&space;of&space;pitch&newline;9&tab;-&tab;-&tab;-&tab;4.0&tab;;RP&space;LHW&space;top&space;of&space;pitch&space;PM&space;#9&space;30cm&space;from&space;spit&space;&tab;&newline;&newline;;-----------&newline;;Question&space;Mark&space;List&newline;&newline;;(leave&space;commented-out)&newline;;grade(A/B/C/X)&space;&space;nearest-station&space;&space;description&newline;;C&space;6&space;small&space;but&space;doable&space;pitch&space;4-7&space;second&space;rattle&newline;;B&space;7&space;north&space;end&space;of&space;parallel&space;rift&newline;;B&space;7&space;south&space;end&space;of&space;parallel&space;rift&newline;;B&space;8&space;passage&space;continuing&space;underneath&space;pitch&newline;&newline;&newline;;------------&newline;;Cave&space;description&newline;&newline;;(leave&space;commented-out)&newline;;freeform&space;text&space;describing&space;this&space;section&space;of&space;the&space;cave&newline;&newline;&newline;*end&space;gosserwager&newline;*file_end&space;&quot;/home/martin/Repositories/loser/caves/264/gosserwager.svx&quot;&space;&quot;&quot;</pctext>
		</pathcodes>
		<pt X="-16.877777" Y="-189.32222"/>
		<pt X="-20.683804" Y="-208.45639"/>
		<pt X="-31.522438" Y="-224.67755"/>
		<pt X="-47.743607" Y="-235.51619"/>
		<pt X="-66.87778" Y="-239.32222"/>
		<pt X="-86.01195" Y="-235.51619"/>
		<pt X="-102.233116" Y="-224.67755"/>
		<pt X="-113.07175" Y="-208.45639"/>
		<pt X="-116.87778" Y="-189.32222"/>
		<pt X="-113.07175" Y="-170.18805"/>
		<pt X="-102.233116" Y="-153.96689"/>
		<pt X="-86.01195" Y="-143.12825"/>
		<pt X="-66.87778" Y="-139.32222"/>
		<pt X="-47.743607" Y="-135.51619"/>
		<pt X="-31.522438" Y="-124.67756"/>
		<pt X="-20.683804" Y="-108.45639"/>
		<pt X="-16.877777" Y="-89.32222"/>
		<pt X="-20.683804" Y="-70.18805"/>
		<pt X="-31.522438" Y="-53.966873"/>
		<pt X="-47.743607" Y="-43.12825"/>
		<pt X="-66.87778" Y="-39.32222"/>
		<pt X="-86.01195" Y="-43.12825"/>
		<pt X="-102.233116" Y="-53.966873"/>
		<pt X="-113.07175" Y="-70.18805"/>
		<pt X="-116.87778" Y="-89.32222"/>
	</skpath>
	<skpath from="3" to="2" linestyle="centreline">
		<pathcodes>
			<cl_stations tail="gosserwager.9" head="gosserwager.8"/>
			<pctext style="" nodeposxrel="-1.0" nodeposyrel="-1.0"></pctext>
		</pathcodes>
		<sketchsubset subname="Gosser Wager"/>
		<pt X="10.722222" Y="98.87778" Z="61.6"/>
		<pt X="10.722222" Y="98.87778" Z="-34.9"/>
	</skpath>
	<skpath from="4" to="4" linestyle="connective">
		<pathcodes>
			<pctext style="" nodeposxrel="-1.0" nodeposyrel="-1.0"></pctext>
			<pcarea area_signal="frame" sfscaledown="4.7345777" sfrotatedeg="0.438912" sfelevrotdeg="0.0" sfelevvertplane="" sfxtrans="-24.752802200827055" sfytrans="-29.06635993014127" sfsketch="surveyscans/2015/2015/2015#23-264 Gosser Wager/plan.png" sfstyle="" nodeconnzsetrelative="0.0" sfpixwidth="2550" sfpixheight="3501">
			</pcarea>
		</pathcodes>
		<pt X="-260.2058" Y="-301.58582"/>
		<pt X="278.3692" Y="-305.71164"/>
		<pt X="284.0337" Y="433.72015"/>
		<pt X="-254.5413" Y="437.84598"/>
		<pt X="-260.2058" Y="-301.58582"/>
	</skpath>
	<skpath from="5" to="2" linestyle="centreline">
		<pathcodes>
			<cl_stations tail="gosserwager.7" head="gosserwager.8"/>
			<pctext style="" nodeposxrel="-1.0" nodeposyrel="-1.0"></pctext>
		</pathcodes>
		<sketchsubset subname="Gosser Wager"/>
		<pt X="13.411956" Y="77.02967" Z="-18.8"/>
		<pt X="10.722222" Y="98.87778" Z="-34.9"/>
	</skpath>
	<skpath from="6" to="5" linestyle="centreline">
		<pathcodes>
			<cl_stations tail="gosserwager.6" head="gosserwager.7"/>
			<pctext style="" nodeposxrel="-1.0" nodeposyrel="-1.0"></pctext>
		</pathcodes>
		<sketchsubset subname="Gosser Wager"/>
		<pt X="10.1890335" Y="-8.602639" Z="-9.8"/>
		<pt X="13.411956" Y="77.02967" Z="-18.8"/>
	</skpath>
	<skpath from="7" to="6" linestyle="centreline">
		<pathcodes>
			<cl_stations tail="gosserwager.1" head="gosserwager.6"/>
			<pctext style="" nodeposxrel="-1.0" nodeposyrel="-1.0"></pctext>
		</pathcodes>
		<sketchsubset subname="Gosser Wager"/>
		<pt X="-12.221523" Y="-10.738763" Z="-20.3"/>
		<pt X="10.1890335" Y="-8.602639" Z="-9.8"/>
	</skpath>
	<skpath from="7" to="8" linestyle="centreline">
		<pathcodes>
			<cl_stations tail="gosserwager.1" head="gosserwager.2"/>
			<pctext style="" nodeposxrel="-1.0" nodeposyrel="-1.0"></pctext>
		</pathcodes>
		<sketchsubset subname="Gosser Wager"/>
		<pt X="-12.221523" Y="-10.738763" Z="-20.3"/>
		<pt X="-13.420751" Y="-37.196712" Z="-10.700001"/>
	</skpath>
	<skpath from="8" to="9" linestyle="centreline">
		<pathcodes>
			<cl_stations tail="gosserwager.2" head="gosserwager.3"/>
			<pctext style="" nodeposxrel="-1.0" nodeposyrel="-1.0"></pctext>
		</pathcodes>
		<sketchsubset subname="Gosser Wager"/>
		<pt X="-13.420751" Y="-37.196712" Z="-10.700001"/>
		<pt X="-3.6770303" Y="-53.161423" Z="-1.0"/>
	</skpath>
	<skpath from="9" to="10" linestyle="centreline">
		<pathcodes>
			<cl_stations tail="gosserwager.3" head="gosserwager.5"/>
			<pctext style="" nodeposxrel="-1.0" nodeposyrel="-1.0"></pctext>
		</pathcodes>
		<sketchsubset subname="Gosser Wager"/>
		<pt X="-3.6770303" Y="-53.161423" Z="-1.0"/>
		<pt X="-16.877777" Y="-75.62222" Z="25.1"/>
	</skpath>
	<skpath from="9" to="11" linestyle="centreline">
		<pathcodes>
			<cl_stations tail="gosserwager.3" head="gosserwager.4"/>
			<pctext style="" nodeposxrel="-1.0" nodeposyrel="-1.0"></pctext>
		</pathcodes>
		<sketchsubset subname="Gosser Wager"/>
		<pt X="-3.6770303" Y="-53.161423" Z="-1.0"/>
		<pt X="0.62222224" Y="-89.32222" Z="8.8"/>
	</skpath>
	<skpath from="10" to="12" linestyle="connective">
		<pt X="-16.877777" Y="-75.62222" Z="25.1"/>
		<pt X="-17.39319" Y="-76.321495"/>
	</skpath>
	<skpath from="11" to="13" linestyle="connective">
		<pt X="0.62222224" Y="-89.32222" Z="8.8"/>
		<pt X="0.96997476" Y="-90.52484"/>
	</skpath>
	<skpath from="9" to="14" linestyle="connective">
		<pt X="-3.6770303" Y="-53.161423" Z="-1.0"/>
		<pt X="-0.75391424" Y="-51.437534"/>
	</skpath>
	<skpath from="9" to="15" linestyle="connective">
		<pt X="-3.6770303" Y="-53.161423" Z="-1.0"/>
		<pt X="-10.685014" Y="-52.56181"/>
	</skpath>
	<skpath from="16" to="9" linestyle="connective">
		<pt X="-3.751982" Y="-54.398125"/>
		<pt X="-3.6770303" Y="-53.161423" Z="-1.0"/>
	</skpath>
	<skpath from="17" to="8" linestyle="connective">
		<pt X="-6.712574" Y="-35.622726"/>
		<pt X="-13.420751" Y="-37.196712" Z="-10.700001"/>
	</skpath>
	<skpath from="18" to="8" linestyle="connective">
		<pt X="-13.832985" Y="-38.02118"/>
		<pt X="-13.420751" Y="-37.196712" Z="-10.700001"/>
	</skpath>
	<skpath from="19" to="7" linestyle="connective">
		<pt X="-12.70871" Y="-9.914294"/>
		<pt X="-12.221523" Y="-10.738763" Z="-20.3"/>
	</skpath>
	<skpath from="7" to="20" linestyle="connective">
		<pt X="-12.221523" Y="-10.738763" Z="-20.3"/>
		<pt X="-1.540907" Y="-13.249644"/>
	</skpath>
	<skpath from="21" to="6" linestyle="connective">
		<pt X="9.177185" Y="-7.3284607"/>
		<pt X="10.1890335" Y="-8.602639" Z="-9.8"/>
	</skpath>
	<skpath from="6" to="22" linestyle="connective">
		<pt X="10.1890335" Y="-8.602639" Z="-9.8"/>
		<pt X="14.123998" Y="-13.137217"/>
	</skpath>
	<skpath from="23" to="5" linestyle="connective">
		<pt X="9.476993" Y="76.95472"/>
		<pt X="13.411956" Y="77.02967" Z="-18.8"/>
	</skpath>
	<skpath from="5" to="24" linestyle="connective">
		<pt X="13.411956" Y="77.02967" Z="-18.8"/>
		<pt X="16.709831" Y="77.02967"/>
	</skpath>
	<skpath from="25" to="26" linestyle="connective">
		<pt X="21.169456" Y="77.292"/>
		<pt X="26.865786" Y="77.254524"/>
	</skpath>
	<skpath from="2" to="27" linestyle="connective">
		<pt X="10.722222" Y="98.87778" Z="-34.9"/>
		<pt X="8.615047" Y="98.69071"/>
	</skpath>
	<skpath from="2" to="28" linestyle="connective">
		<pt X="10.722222" Y="98.87778" Z="-34.9"/>
		<pt X="19.97023" Y="99.177895"/>
	</skpath>
	<skpath from="29" to="30" linestyle="connective">
		<pt X="22.368683" Y="97.154205"/>
		<pt X="26.491028" Y="96.10488"/>
	</skpath>
	<skpath from="14" to="13" linestyle="wall" splined="1">
		<pt X="-0.75391424" Y="-51.437534"/>
		<pt X="1.6859423" Y="-57.6457"/>
		<pt X="2.2073526" Y="-67.03108"/>
		<pt X="1.8162948" Y="-83.97691"/>
		<pt X="0.96997476" Y="-90.52484"/>
	</skpath>
	<skpath from="13" to="16" linestyle="wall" splined="1">
		<pt X="0.96997476" Y="-90.52484"/>
		<pt X="-0.79075664" Y="-90.6249"/>
		<pt X="-1.0514618" Y="-84.237625"/>
		<pt X="-2.48534" Y="-65.3365"/>
		<pt X="-2.969018" Y="-57.219635"/>
		<pt X="-3.1322627" Y="-54.73831"/>
		<pt X="-3.751982" Y="-54.398125"/>
	</skpath>
	<skpath from="16" to="12" linestyle="wall" splined="1">
		<pt X="-3.751982" Y="-54.398125"/>
		<pt X="-4.4871945" Y="-54.673016"/>
		<pt X="-4.6830883" Y="-58.03586"/>
		<pt X="-6.1359673" Y="-62.427143"/>
		<pt X="-10.808544" Y="-69.2926"/>
		<pt X="-15.196212" Y="-75.31489"/>
		<pt X="-16.486702" Y="-76.51935"/>
		<pt X="-17.39319" Y="-76.321495"/>
	</skpath>
	<skpath from="12" to="15" linestyle="wall" splined="1">
		<pt X="-17.39319" Y="-76.321495"/>
		<pt X="-17.433062" Y="-75.400925"/>
		<pt X="-16.142572" Y="-72.99201"/>
		<pt X="-12.701263" Y="-65.507164"/>
		<pt X="-10.636479" Y="-59.31281"/>
		<pt X="-10.206315" Y="-55.355305"/>
		<pt X="-10.685014" Y="-52.56181"/>
	</skpath>
	<skpath from="18" to="19" linestyle="wall" splined="1">
		<pt X="-13.832985" Y="-38.02118"/>
		<pt X="-14.335885" Y="-34.535393"/>
		<pt X="-14.163819" Y="-27.13658"/>
		<pt X="-13.475558" Y="-19.909832"/>
		<pt X="-13.131428" Y="-13.199282"/>
		<pt X="-12.70871" Y="-9.914294"/>
	</skpath>
	<skpath from="19" to="21" linestyle="wall" splined="1">
		<pt X="-12.70871" Y="-9.914294"/>
		<pt X="-11.92697" Y="-7.865254"/>
		<pt X="-6.9370728" Y="-4.682044"/>
		<pt X="-1.9471762" Y="-3.1334553"/>
		<pt X="3.6449494" Y="-3.9077497"/>
		<pt X="6.397996" Y="-6.4887304"/>
		<pt X="8.032618" Y="-7.263025"/>
		<pt X="9.177185" Y="-7.3284607"/>
	</skpath>
	<skpath from="21" to="31" linestyle="wall" splined="1">
		<pt X="9.177185" Y="-7.3284607"/>
		<pt X="10.097402" Y="-6.7468286"/>
		<pt X="10.3555" Y="-5.7144365"/>
	</skpath>
	<skpath from="31" to="32" linestyle="wall" splined="1">
		<pt X="10.3555" Y="-5.7144365"/>
		<pt X="10.097402" Y="-4.423946"/>
		<pt X="10.01137" Y="-1.5848666"/>
		<pt X="10.3555" Y="1.1681798"/>
	</skpath>
	<skpath from="17" to="20" linestyle="wall" splined="1">
		<pt X="-6.712574" Y="-35.622726"/>
		<pt X="-5.9046803" Y="-29.889626"/>
		<pt X="-5.3024516" Y="-24.469564"/>
		<pt X="-3.8398957" Y="-19.135538"/>
		<pt X="-1.540907" Y="-13.249644"/>
	</skpath>
	<skpath from="20" to="22" linestyle="wall" splined="1">
		<pt X="-1.540907" Y="-13.249644"/>
		<pt X="-0.57065296" Y="-10.962431"/>
		<pt X="3.3868513" Y="-10.27417"/>
		<pt X="6.139898" Y="-11.994823"/>
		<pt X="9.495173" Y="-14.7478695"/>
		<pt X="11.30186" Y="-14.919935"/>
		<pt X="13.108546" Y="-14.145641"/>
		<pt X="14.123998" Y="-13.137217"/>
	</skpath>
	<skpath from="22" to="33" linestyle="wall" splined="1">
		<pt X="14.123998" Y="-13.137217"/>
		<pt X="15.001266" Y="-11.134497"/>
		<pt X="15.087298" Y="-4.337913"/>
	</skpath>
	<skpath from="33" to="34" linestyle="wall" splined="1">
		<pt X="15.087298" Y="-4.337913"/>
		<pt X="16.119692" Y="-0.036278073"/>
	</skpath>
	<skpath from="36" to="26" linestyle="wall" splined="1">
		<pt X="24.98888" Y="57.60563"/>
		<pt X="24.46747" Y="62.298325"/>
		<pt X="24.98888" Y="65.42679"/>
		<pt X="26.813816" Y="67.251724"/>
		<pt X="27.335226" Y="71.29265"/>
		<pt X="26.865786" Y="77.254524"/>
	</skpath>
	<skpath from="26" to="30" linestyle="wall" splined="1">
		<pt X="26.865786" Y="77.254524"/>
		<pt X="26.0317" Y="84.588615"/>
		<pt X="26.491028" Y="96.10488"/>
	</skpath>
	<skpath from="30" to="37" linestyle="wall" splined="1">
		<pt X="26.491028" Y="96.10488"/>
		<pt X="27.465578" Y="100.62198"/>
	</skpath>
	<skpath from="38" to="29" linestyle="wall" splined="1">
		<pt X="22.642534" Y="103.35938"/>
		<pt X="22.368683" Y="97.154205"/>
	</skpath>
	<skpath from="23" to="39" linestyle="wall" splined="1">
		<pt X="9.476993" Y="76.95472"/>
		<pt X="9.346571" Y="79.635216"/>
		<pt X="7.26093" Y="84.3279"/>
		<pt X="2.8289428" Y="90.71519"/>
		<pt X="0.612949" Y="96.97211"/>
		<pt X="0.48259643" Y="101.01304"/>
		<pt X="1.9164747" Y="103.88079"/>
		<pt X="4.523526" Y="104.923615"/>
		<pt X="8.303751" Y="106.22714"/>
	</skpath>
	<skpath from="39" to="40" linestyle="wall" splined="1">
		<pt X="8.303751" Y="106.22714"/>
		<pt X="8.564456" Y="111.571594"/>
	</skpath>
	<skpath from="28" to="41" linestyle="wall" splined="1">
		<pt X="19.97023" Y="99.177895"/>
		<pt X="19.774776" Y="104.27185"/>
		<pt X="20.687244" Y="110.78948"/>
	</skpath>
	<skpath from="28" to="42" linestyle="invisible" splined="1">
		<pt X="19.97023" Y="99.177895"/>
		<pt X="16.124905" Y="95.14717"/>
	</skpath>
	<skpath from="28" to="29" linestyle="wall" splined="1">
		<pt X="19.97023" Y="99.177895"/>
		<pt X="19.383718" Y="92.54012"/>
		<pt X="20.035482" Y="88.49919"/>
		<pt X="21.339008" Y="88.89025"/>
		<pt X="22.368683" Y="97.154205"/>
	</skpath>
	<skpath from="42" to="42" linestyle="pitchbound" splined="1">
		<pt X="16.124905" Y="95.14717"/>
		<pt X="15.212437" Y="97.23281"/>
		<pt X="12.866091" Y="98.275635"/>
		<pt X="12.083976" Y="95.53823"/>
		<pt X="12.735738" Y="91.236595"/>
		<pt X="14.430322" Y="89.67236"/>
		<pt X="16.776669" Y="90.454475"/>
		<pt X="16.776669" Y="93.58294"/>
		<pt X="16.124905" Y="95.14717"/>
	</skpath>
	<skpath from="39" to="27" linestyle="detail" splined="1">
		<pt X="8.303751" Y="106.22714"/>
		<pt X="8.615047" Y="98.69071"/>
	</skpath>
	<skpath from="43" to="44" linestyle="detail" splined="1">
		<pt X="10.78045" Y="107.53066"/>
		<pt X="17.037373" Y="111.050186"/>
	</skpath>
	<skpath from="44" to="45" linestyle="detail" splined="1">
		<pt X="17.037373" Y="111.050186"/>
		<pt X="19.644424" Y="106.22714"/>
	</skpath>
	<skpath from="45" to="43" linestyle="detail">
		<pt X="19.644424" Y="106.22714"/>
		<pt X="14.560675" Y="103.48974"/>
		<pt X="10.78045" Y="107.53066"/>
	</skpath>
	<skpath from="46" to="44" linestyle="detail">
		<pt X="17.689137" Y="114.309"/>
		<pt X="17.037373" Y="111.050186"/>
	</skpath>
	<skpath from="46" to="43" linestyle="detail">
		<pt X="17.689137" Y="114.309"/>
		<pt X="11.30186" Y="110.91983"/>
		<pt X="10.78045" Y="107.53066"/>
	</skpath>
	<skpath from="46" to="45" linestyle="detail">
		<pt X="17.689137" Y="114.309"/>
		<pt X="20.165834" Y="110.13772"/>
		<pt X="19.644424" Y="106.22714"/>
	</skpath>
	<skpath from="39" to="43" linestyle="invisible" splined="1">
		<pt X="8.303751" Y="106.22714"/>
		<pt X="10.78045" Y="107.53066"/>
	</skpath>
	<skpath from="40" to="41" linestyle="invisible" splined="1">
		<pt X="8.564456" Y="111.571594"/>
		<pt X="12.866091" Y="117.43746"/>
		<pt X="19.123014" Y="116.65534"/>
		<pt X="20.687244" Y="110.78948"/>
	</skpath>
	<skpath from="38" to="37" linestyle="invisible" splined="1">
		<pt X="22.642534" Y="103.35938"/>
		<pt X="27.465578" Y="100.62198"/>
	</skpath>
	<skpath from="35" to="36" linestyle="invisible" splined="1">
		<pt X="21.208656" Y="55.51999"/>
		<pt X="24.98888" Y="57.60563"/>
	</skpath>
	<skpath from="24" to="47" linestyle="wall" splined="1">
		<pt X="16.709831" Y="77.02967"/>
		<pt X="16.90702" Y="73.899704"/>
		<pt X="17.689137" Y="69.98913"/>
		<pt X="18.189783" Y="69.06118"/>
	</skpath>
	<skpath from="47" to="25" linestyle="wall" splined="1">
		<pt X="18.189783" Y="69.06118"/>
		<pt X="18.862309" Y="68.6856"/>
		<pt X="20.687244" Y="70.38018"/>
		<pt X="21.208656" Y="74.03005"/>
		<pt X="21.169456" Y="77.292"/>
	</skpath>
	<skpath from="34" to="48" linestyle="wall" splined="1">
		<pt X="16.119692" Y="-0.036278073"/>
		<pt X="16.205723" Y="3.9212263"/>
		<pt X="16.119692" Y="12.610529"/>
		<pt X="16.377789" Y="23.79478"/>
		<pt X="15.994553" Y="35.054634"/>
		<pt X="15.082085" Y="48.089893"/>
		<pt X="15.34279" Y="58.257393"/>
		<pt X="16.646315" Y="61.776913"/>
		<pt X="18.116705" Y="61.572243"/>
	</skpath>
	<skpath from="48" to="35" linestyle="wall" splined="1">
		<pt X="18.116705" Y="61.572243"/>
		<pt X="18.862309" Y="60.994797"/>
		<pt X="21.208656" Y="56.69316"/>
		<pt X="21.208656" Y="55.51999"/>
	</skpath>
	<skpath from="48" to="47" linestyle="invisible" splined="1">
		<pt X="18.116705" Y="61.572243"/>
		<pt X="18.189783" Y="69.06118"/>
	</skpath>
	<skpath from="34" to="32" linestyle="pitchbound" splined="1">
		<pt X="16.119692" Y="-0.036278073"/>
		<pt X="15.733848" Y="2.3361397"/>
		<pt X="14.299969" Y="3.9003706"/>
		<pt X="12.344681" Y="4.4217806"/>
		<pt X="10.3555" Y="1.1681798"/>
	</skpath>
	<skpath from="31" to="33" linestyle="pitchbound" splined="1">
		<pt X="10.3555" Y="-5.7144365"/>
		<pt X="11.432213" Y="-7.4403033"/>
		<pt X="13.517854" Y="-6.918893"/>
		<pt X="15.087298" Y="-4.337913"/>
	</skpath>
	<skpath from="19" to="20" linestyle="pitchbound" splined="1">
		<pt X="-12.70871" Y="-9.914294"/>
		<pt X="-11.118782" Y="-11.872291"/>
		<pt X="-6.5564423" Y="-13.5668745"/>
		<pt X="-3.8190384" Y="-13.697227"/>
		<pt X="-1.540907" Y="-13.249644"/>
	</skpath>
	<skpath from="15" to="49" linestyle="wall" splined="1">
		<pt X="-10.685014" Y="-52.56181"/>
		<pt X="-11.496806" Y="-49.074917"/>
	</skpath>
	<skpath from="49" to="18" linestyle="wall" splined="1">
		<pt X="-11.496806" Y="-49.074917"/>
		<pt X="-12.787296" Y="-44.171055"/>
		<pt X="-13.832985" Y="-38.02118"/>
	</skpath>
	<skpath from="17" to="50" linestyle="wall" splined="1">
		<pt X="-6.712574" Y="-35.622726"/>
		<pt X="-6.135212" Y="-40.56951"/>
		<pt X="-2.8763978" Y="-47.08714"/>
		<pt X="-2.5289302" Y="-47.79209"/>
	</skpath>
	<skpath from="50" to="14" linestyle="wall" splined="1">
		<pt X="-2.5289302" Y="-47.79209"/>
		<pt X="-0.75391424" Y="-51.437534"/>
	</skpath>
	<skpath from="50" to="49" linestyle="invisible" splined="1">
		<pt X="-2.5289302" Y="-47.79209"/>
		<pt X="-6.42609" Y="-48.37101"/>
		<pt X="-11.496806" Y="-49.074917"/>
	</skpath>
	<skpath from="51" to="25" linestyle="connective">
		<pathcodes>
			<pctext style="" nodeposxrel="-1.0" nodeposyrel="-1.0"></pctext>
			<pcarea area_signal="rock"/>
		</pathcodes>
		<pt X="18.056492" Y="76.242096"/>
		<pt X="21.169456" Y="77.292"/>
	</skpath>
	<skpath from="25" to="52" linestyle="wall" splined="1">
		<pt X="21.169456" Y="77.292"/>
		<pt X="20.817598" Y="80.54768"/>
		<pt X="19.774776" Y="83.54579"/>
		<pt X="18.080194" Y="83.67615"/>
		<pt X="16.646315" Y="80.41733"/>
	</skpath>
	<skpath from="52" to="24" linestyle="wall" splined="1">
		<pt X="16.646315" Y="80.41733"/>
		<pt X="16.709831" Y="77.02967"/>
	</skpath>
	<skpath from="23" to="53" linestyle="detail" splined="1">
		<pt X="9.476993" Y="76.95472"/>
		<pt X="10.020891" Y="80.93832"/>
	</skpath>
	<skpath from="53" to="27" linestyle="detail" splined="1">
		<pt X="10.020891" Y="80.93832"/>
		<pt X="10.128687" Y="83.415436"/>
		<pt X="8.615047" Y="98.69071"/>
	</skpath>
	<skpath from="32" to="54" linestyle="wall" splined="1">
		<pt X="10.3555" Y="1.1681798"/>
		<pt X="10.78045" Y="9.505531"/>
		<pt X="10.78045" Y="25.799603"/>
		<pt X="11.30186" Y="36.358162"/>
		<pt X="10.519745" Y="58.387745"/>
		<pt X="9.607277" Y="67.77313"/>
		<pt X="9.538122" Y="69.18702"/>
	</skpath>
	<skpath from="54" to="23" linestyle="wall" splined="1">
		<pt X="9.538122" Y="69.18702"/>
		<pt X="9.476993" Y="76.95472"/>
	</skpath>
	<skpath from="54" to="47" linestyle="invisible" splined="1">
		<pt X="9.538122" Y="69.18702"/>
		<pt X="13.7586" Y="71.22955"/>
		<pt X="17.33584" Y="69.242195"/>
		<pt X="18.189783" Y="69.06118"/>
	</skpath>
	<skpath from="47" to="55" linestyle="connective">
		<pathcodes>
			<pctext style="" nodeposxrel="-1.0" nodeposyrel="-1.0"></pctext>
			<pcsymbol rname="boulders"/>
		</pathcodes>
		<pt X="18.189783" Y="69.06118"/>
		<pt X="13.589864" Y="63.636467"/>
		<pt X="12.207336" Y="7.3478594"/>
	</skpath>
	<skpath from="56" to="40" linestyle="connective">
		<pathcodes>
			<pctext style="qm" nodeposxrel="0.0" nodeposyrel="1.0">15-?B</pctext>
		</pathcodes>
		<pt X="10.429802" Y="125.455185"/>
		<pt X="7.8622513" Y="121.1101"/>
		<pt X="8.564456" Y="111.571594"/>
	</skpath>
	<skpath from="57" to="37" linestyle="connective">
		<pathcodes>
			<pctext style="qm" nodeposxrel="-1.0" nodeposyrel="-1.0">15-?B</pctext>
		</pathcodes>
		<pt X="38.223984" Y="111.01945"/>
		<pt X="27.465578" Y="100.62198"/>
	</skpath>
	<skpath from="58" to="36" linestyle="connective">
		<pathcodes>
			<pctext style="qm" nodeposxrel="-1.0" nodeposyrel="-1.0">15-?B</pctext>
		</pathcodes>
		<pt X="23.860065" Y="53.863018"/>
		<pt X="24.98888" Y="57.60563"/>
	</skpath>
	<skpath from="59" to="34" linestyle="connective">
		<pathcodes>
			<pctext style="qm" nodeposxrel="-1.0" nodeposyrel="-1.0">15-?C</pctext>
		</pathcodes>
		<pt X="18.701025" Y="-2.8744593"/>
		<pt X="16.119692" Y="-0.036278073"/>
	</skpath>
	<skpath from="60" to="13" linestyle="connective">
		<pathcodes>
			<pctext style="passage" nodeposxrel="-1.0" nodeposyrel="-1.0">G&ouml;sser&space;Wager</pctext>
		</pathcodes>
		<pt X="10.860719" Y="-96.26986"/>
		<pt X="0.96997476" Y="-90.52484"/>
	</skpath>
	<skpath from="22" to="61" linestyle="connective">
		<pathcodes>
			<pctext style="" nodeposxrel="-1.0" nodeposyrel="-1.0"></pctext>
			<pcsymbol rname="boulders"/>
		</pathcodes>
		<pt X="14.123998" Y="-13.137217"/>
		<pt X="-4.8896894" Y="-5.768019"/>
	</skpath>
	<skpath from="19" to="62" linestyle="connective">
		<pathcodes>
			<pctext style="" nodeposxrel="-1.0" nodeposyrel="-1.0"></pctext>
			<pcsymbol rname="boulders"/>
			<pcsymbol rname="sand"/>
		</pathcodes>
		<pt X="-12.70871" Y="-9.914294"/>
		<pt X="-6.8684416" Y="-46.54752"/>
	</skpath>
	<skpath from="50" to="63" linestyle="connective">
		<pathcodes>
			<pctext style="" nodeposxrel="-1.0" nodeposyrel="-1.0"></pctext>
			<pcsymbol rname="boulders"/>
		</pathcodes>
		<pt X="-2.5289302" Y="-47.79209"/>
		<pt X="-12.546599" Y="-68.74396"/>
	</skpath>
</sketch>
</tunnelxml>
